AspNetDocumentation/README.md
AspNetDocumentation/__init__.py
AspNetDocumentation/__main__.py
AspNetDocumentation/file.epub
AspNetDocumentation/index.html
AspNetDocumentation/css/__init__.py
AspNetDocumentation/css/annotations.css
AspNetDocumentation/css/main.css
AspNetDocumentation/css/normalize.css
AspNetDocumentation/css/popup.css
AspNetDocumentation/font/__init__.py
AspNetDocumentation/font/fontello.eot
AspNetDocumentation/font/fontello.svg
AspNetDocumentation/font/fontello.ttf
AspNetDocumentation/font/fontello.woff
AspNetDocumentation/img/__init__.py
AspNetDocumentation/img/annotator-glyph-sprite.png
AspNetDocumentation/img/annotator-icon-sprite.png
AspNetDocumentation/img/apple-touch-icon.png
AspNetDocumentation/img/cancelfullscreen.png
AspNetDocumentation/img/close.png
AspNetDocumentation/img/fullscreen.png
AspNetDocumentation/img/loader.gif
AspNetDocumentation/img/menu-icon.png
AspNetDocumentation/img/save.png
AspNetDocumentation/img/saved.png
AspNetDocumentation/img/settings-s.png
AspNetDocumentation/img/settings.png
AspNetDocumentation/img/star.png
AspNetDocumentation/js/__init__.py
AspNetDocumentation/js/epub.js
AspNetDocumentation/js/epub.min.js
AspNetDocumentation/js/epub.min.map
AspNetDocumentation/js/hooks.min.js
AspNetDocumentation/js/hooks.min.map
AspNetDocumentation/js/reader.js
AspNetDocumentation/js/reader.js.map
AspNetDocumentation/js/reader.min.js
AspNetDocumentation/js/reader.min.map
AspNetDocumentation/js/hooks/__init__.py
AspNetDocumentation/js/hooks/extensions/__init__.py
AspNetDocumentation/js/hooks/extensions/highlight.js
AspNetDocumentation/js/libs/__init__.py
AspNetDocumentation/js/libs/jquery.min.js
AspNetDocumentation/js/libs/localforage.min.js
AspNetDocumentation/js/libs/screenfull.js
AspNetDocumentation/js/libs/screenfull.min.js
AspNetDocumentation/js/libs/zip.min.js
AspNetDocumentation/js/plugins/__init__.py
AspNetDocumentation/js/plugins/hypothesis.js
AspNetDocumentation/js/plugins/search.js
asp_net_documentation-2024.2.29.0.dist-info/METADATA
asp_net_documentation-2024.2.29.0.dist-info/WHEEL
asp_net_documentation-2024.2.29.0.dist-info/entry_points.txt
asp_net_documentation-2024.2.29.0.dist-info/top_level.txt
asp_net_documentation-2024.2.29.0.dist-info/RECORD
